pyority_queue/__init__.py
pyority_queue/heartbeat.py
pyority_queue/records.py
pyority_queue/task_handler.py
pyority_queue/enums/__init__.py
pyority_queue/enums/status_codes.py
pyority_queue/enums/statuses.py
pyority_queue/errors/__init__.py
pyority_queue/errors/empty_queue_error.py
pyority_queue/logger/__init__.py
pyority_queue/logger/json_logger.py
mc_pyority_queue-1.0.1.dist-info/LICENSE
mc_pyority_queue-1.0.1.dist-info/METADATA
mc_pyority_queue-1.0.1.dist-info/WHEEL
mc_pyority_queue-1.0.1.dist-info/top_level.txt
mc_pyority_queue-1.0.1.dist-info/RECORD
