Metadata-Version: 2.1
Name: mc-pyority-queue
Version: 1.0.1
Summary: Map colonies priority queue management service for records
Home-page: https://github.com/MapColonies/pyority-queue.git
Author: MC
License: UNKNOWN
Platform: UNKNOWN
Classifier: Programming Language :: Python :: 3
Classifier: License :: OSI Approved :: MIT License
Classifier: Operating System :: OS Independent
Requires-Python: >=3.6
Requires-Dist: wheel
Requires-Dist: aiohttp
Requires-Dist: setuptools (~=50.3.2)
